{
  "cards": [
    {
        "id": 1011,
        "character_id": 20,
        "character_name": "晓山瑞希",
        "unit": "school_refusal",
        "release_at": 1728723600000,
        "supply_type": "非限定",
        "card_rarity_type": "rarity_4",
        "attr": "cute",
        "prefix": "失われてしまったもの",
        "assetbundle_name": "res020_no038",
        "skill_type": "score_up"
    },
    {
        "id": 1252,
        "character_id": 5,
        "character_name": "花里みのり",
        "unit": "idol",
        "release_at": 1759201200000,
        "supply_type": "BFes限定",
        "card_rarity_type": "rarity_4",
        "attr":"cute",
        "prefix": "キラキラのアイドル！",
        "assetbundle_name": "res005_no047",
        "skill_type": "score_up"
    }
  ],
  "region": "jp",
  "card_thumbnail_paths": [
    "card/thumbnails/res020_no038_normal.png",
    "card/thumbnails/res020_no038_after_training.png",
    "card/thumbnails/res005_no047_normal.png",
    "card/thumbnails/res005_no047_after_training.png"
  ],
  "card_skill_icon_paths": [
    "skill/skill_score_up.png"
  ]
}